ws_hash/__init__.py
ws_hash/ws_hash.py
ws_hash-1.0.0.dist-info/LICENSE
ws_hash-1.0.0.dist-info/METADATA
ws_hash-1.0.0.dist-info/WHEEL
ws_hash-1.0.0.dist-info/top_level.txt
ws_hash-1.0.0.dist-info/RECORD
