Metadata-Version: 2.1
Name: ws_hash
Version: 1.0.0
Summary: A simple yet hash library implemented in Python, featuring both 256-bit and 512-bit hash functions.
Home-page: https://github.com/VallionXD/ws-hash/
Author: VallionXD
Author-email: your.email@example.com
Classifier: Programming Language :: Python :: 3
Classifier: License :: OSI Approved :: GNU General Public License v3 (GPLv3)
Classifier: Operating System :: OS Independent
Requires-Python: >=3.6
License-File: LICENSE
